MANIFEST.in
Readme.md
setup.cfg
setup.py
pykeeper/__init__.py
pykeeper/client.py
pykeeper/event.py
pykeeper/log_stream.py
pykeeper.egg-info/PKG-INFO
pykeeper.egg-info/SOURCES.txt
pykeeper.egg-info/dependency_links.txt
pykeeper.egg-info/top_level.txt
pykeeper/test/__init__.py
pykeeper/test/test_client.py
pykeeper/test/test_event.py