Metadata-Version: 1.0
Name: pykeeper
Version: 0.2.1
Summary: Higher-level bindings for ZooKeeper.
Home-page: http://github.com/nkvoll/pykeeper
Author: Njal Karevoll
Author-email: njal@karevoll.no
License: MIT
Keywords: zookeeper
Platform: UNKNOWN
Classifier: Development Status :: 4 - Beta
Classifier: License :: OSI Approved :: MIT License
Classifier: Intended Audience :: Developers
Classifier: Intended Audience :: System Administrators
Classifier: Programming Language :: Python :: 2.6
Classifier: Programming Language :: Python :: 2.7
